utail_filehash/__init__.py
utail_filehash/utfile_hash.py
utailFileHash-0.4.5.dist-info/LICENSE
utailFileHash-0.4.5.dist-info/METADATA
utailFileHash-0.4.5.dist-info/WHEEL
utailFileHash-0.4.5.dist-info/top_level.txt
utailFileHash-0.4.5.dist-info/RECORD
