Metadata-Version: 2.1
Name: utailFileHash
Version: 0.4.5
Summary: make hash
Home-page: https://...
Author: chase
Author-email: 
License: UNKNOWN
Download-URL: https://...
Keywords: utail,file,hash
Platform: UNKNOWN
Classifier: Programming Language :: Python :: 3
Classifier: Programming Language :: Python :: 3.2
Classifier: Programming Language :: Python :: 3.3
Classifier: Programming Language :: Python :: 3.4
Classifier: Programming Language :: Python :: 3.5
Classifier: Programming Language :: Python :: 3.6
Classifier: Programming Language :: Python :: 3.7
Requires-Python: >=3
